{"functions":{"sticker":15336,"taPago":9990,"beijo":8899,"presente":6353,"roletaRussa":4421,"tts":3194,"tcm":4716,"taCago":5490,"movieApi":2443,"stickerBg":1240,"catApi":996,"duckApi":798,"bomDia":819,"cancelTaPago":412,"vddOuCons":722,"addTaPago":465,"geradorquenga":709,"geradorpatriota":582,"taPagoNerd":423,"dogApi":614,"groupRemove":560,"geradornóia":725,"@d#":481,"tvShowApi":445,"taPagoAlimentacao":319,"gerador":503,"geradorcachaceiro":466,"geradortrevoso":450,"geradorsapatão":415,"geradoresquerdopata":355,"geradordrag":328,"everyone":312,"geradorgenocida":309,"userSettingsUpdate":182,"todayApod":230,"dateApod":222,"userSettingsAuthor":139,"taPagoInvest":111,"groupDesc":119,"toggleAdm":114,"randomApod":94,"userSettingsAll":95,"openCloseGroup":72,"userSettingsUser":76,"groupAdd":73,"groupSettingsUpdate":58,"grouplink":53,"rastreioCorreios":75,"printGroupKeyValue":42,"userSettingsMenu":49,"userSettingsDelete":21,"groupSettingsMenu":5,"taPagoCardio":58,"userSettingsClear":9,"taPagoMenu":20,"historicoMenstrual":6,"historicoAnsiodoron":6,"historicoCreatina":5,"historicoMinoxidil":10,"groupSettingsClear":1}}